lorahub/__init__.py
lorahub/algorithm.py
lorahub/constant.py
lorahub-0.1.0.dist-info/LICENSE
lorahub-0.1.0.dist-info/METADATA
lorahub-0.1.0.dist-info/WHEEL
lorahub-0.1.0.dist-info/top_level.txt
lorahub-0.1.0.dist-info/RECORD
