Metadata-Version: 2.1
Name: lorahub
Version: 0.1.0
Summary: Lorahub
Author-email: Lorahub team <liuqian@sea.com>
Project-URL: Homepage, https://github.com/sail-sg/lorahub
Project-URL: Bug Tracker, https://github.com/sail-sg/lorahub/issues
Classifier: Programming Language :: Python :: 3
Classifier: License :: OSI Approved :: MIT License
Classifier: Operating System :: OS Independent
Requires-Python: >=3.7
License-File: LICENSE
Requires-Dist: transformers
Requires-Dist: peft
Requires-Dist: nevergrad
Requires-Dist: torch
Requires-Dist: pandas
Requires-Dist: numpy
Requires-Dist: dataset
